{
  "form_id": "MARK_mark1a",
  "map": {
    "Text1": {
      "key": "disclaimer.disclaimed_portion_description.line1",
      "field_type": "text",
      "page": 0,
      "confidence": "high",
      "label": "A. I hereby disclaim the exclusive right to (describe portion of text or feature disclaimed) — line 1"
    },
    "Text2": {
      "key": "disclaimer.disclaimed_portion_description.line2",
      "field_type": "text",
      "page": 0,
      "confidence": "high",
      "label": "A. (continuation) — line 2"
    },
    "Text3": {
      "key": "mark.text_words.line1",
      "field_type": "text",
      "page": 0,
      "confidence": "high",
      "label": "B.1. TEXT - list word(s) to be protected, if any (if none, so indicate) — line 1"
    },
    "Text4": {
      "key": "mark.text_words.line2",
      "field_type": "text",
      "page": 0,
      "confidence": "high",
      "label": "B.1. TEXT (continuation) — line 2"
    },
    "Text5": {
      "key": "mark.design_features.line1",
      "field_type": "text",
      "page": 0,
      "confidence": "high",
      "label": "B.2. FEATURES - describe in detail the design to be protected, if any (if none, so indicate) — line 1"
    },
    "Text6": {
      "key": "mark.design_features.line2",
      "field_type": "text",
      "page": 0,
      "confidence": "high",
      "label": "B.2. FEATURES (continuation) — line 2"
    },
    "Check Box9": {
      "key": "mark.type",
      "widgets": [
        "Check Box9",
        "Check Box10",
        "Check Box11",
        "Check Box12",
        "Check Box13"
      ],
      "field_type": "text",
      "page": 0,
      "confidence": "high",
      "label": "C. TYPE OF MARK: Trademark - a mark applied to goods applicant manufactures or sells"
    },
    "Text8": {
      "key": "filing.date_signed",
      "field_type": "text",
      "page": 0,
      "confidence": "high",
      "label": "Dated:"
    }
  },
  "built_against_sha256": "53573783cb218cf2911da1e7496888fd61fb5966a0e0ed9f8906fcfc7cd993a2"
}
